schemagic/core.py
schemagic/func.py
schemagic/scratch.py
schemagic/utils.py
schemagic/validators.py
schemagic/web.py
schemagic/__init__.py
schemagic-0.9.1.dist-info/DESCRIPTION.rst
schemagic-0.9.1.dist-info/METADATA
schemagic-0.9.1.dist-info/metadata.json
schemagic-0.9.1.dist-info/RECORD
schemagic-0.9.1.dist-info/top_level.txt
schemagic-0.9.1.dist-info/WHEEL
