Metadata-Version: 2.0
Name: schemagic
Version: 0.9.1
Summary: Define the shape of your data with simple python data structures. Use those data descriptions to validate your application.
Home-page: https://github.com/Mechrophile/schemagic
Author: Tyler Tolton
Author-email: tjtolton@gmail.com
License: LGPL
Keywords: schema,schemas,schemata,validate,validation,validatorjson,REST,webservice,flask,POSTagile
Platform: UNKNOWN
